leancloud/__init__.py
leancloud/acl.py
leancloud/app_router.py
leancloud/client.py
leancloud/cloud.py
leancloud/conversation.py
leancloud/errors.py
leancloud/file_.py
leancloud/geo_point.py
leancloud/message.py
leancloud/object_.py
leancloud/operation.py
leancloud/push.py
leancloud/query.py
leancloud/relation.py
leancloud/role.py
leancloud/status.py
leancloud/sys_message.py
leancloud/user.py
leancloud/utils.py
leancloud/engine/__init__.py
leancloud/engine/authorization.py
leancloud/engine/context.py
leancloud/engine/cookie_session.py
leancloud/engine/cors.py
leancloud/engine/https_redirect_middleware.py
leancloud/engine/leanengine.py
leancloud/engine/utils.py
leancloud-3.0.2.dist-info/LICENSE
leancloud-3.0.2.dist-info/METADATA
leancloud-3.0.2.dist-info/WHEEL
leancloud-3.0.2.dist-info/top_level.txt
leancloud-3.0.2.dist-info/RECORD
